setup.py
omar_khalil_probability_package/Binomialdistribution.py
omar_khalil_probability_package/Gaussiandistribution.py
omar_khalil_probability_package/Generaldistribution.py
omar_khalil_probability_package/__init__.py
omar_khalil_probability_package.egg-info/PKG-INFO
omar_khalil_probability_package.egg-info/SOURCES.txt
omar_khalil_probability_package.egg-info/dependency_links.txt
omar_khalil_probability_package.egg-info/not-zip-safe
omar_khalil_probability_package.egg-info/top_level.txt