Metadata-Version: 2.1
Name: omar-khalil-probability-package
Version: 2.0
Summary: Gaussian and Bionomial distributions ND
Author: Omar Khalil
Author-email: omar.khalil498@gmail.com
